odoo/addons/bank_statement_check_number/README.rst
odoo/addons/bank_statement_check_number/__init__.py
odoo/addons/bank_statement_check_number/__manifest__.py
odoo/addons/bank_statement_check_number/i18n/bank_statement_check_number.pot
odoo/addons/bank_statement_check_number/i18n/sv.po
odoo/addons/bank_statement_check_number/models/__init__.py
odoo/addons/bank_statement_check_number/models/account_bank_statement.py
odoo/addons/bank_statement_check_number/readme/CONTRIBUTORS.rst
odoo/addons/bank_statement_check_number/readme/DESCRIPTION.rst
odoo/addons/bank_statement_check_number/static/description/icon.png
odoo/addons/bank_statement_check_number/static/description/index.html
odoo/addons/bank_statement_check_number/views/account_bank_statement_views.xml
odoo14_addon_bank_statement_check_number-14.0.1.0.1.dev5.dist-info/METADATA
odoo14_addon_bank_statement_check_number-14.0.1.0.1.dev5.dist-info/WHEEL
odoo14_addon_bank_statement_check_number-14.0.1.0.1.dev5.dist-info/top_level.txt
odoo14_addon_bank_statement_check_number-14.0.1.0.1.dev5.dist-info/RECORD
